LICENSE
MANIFEST.in
README.md
setup.py
feelingtweets/__init__.py
feelingtweets/__main__.py
feelingtweets.egg-info/PKG-INFO
feelingtweets.egg-info/SOURCES.txt
feelingtweets.egg-info/dependency_links.txt
feelingtweets.egg-info/requires.txt
feelingtweets.egg-info/top_level.txt
feelingtweets/analizer/__init__.py
feelingtweets/analizer/analizer.py
feelingtweets/analizer/textblob_analizer.py
feelingtweets/analizer/vader_analizer.py
feelingtweets/cleaner/__init__.py
feelingtweets/cleaner/cleaner.py
feelingtweets/collector/__init__.py
feelingtweets/collector/scrapper.py
feelingtweets/collector/tweetCollector.py
feelingtweets/traductor/__init__.py
feelingtweets/traductor/traductor.py
feelingtweets/utils/__init__.py
feelingtweets/utils/config.py
feelingtweets/utils/query.py
feelingtweets/utils/writter.py